usabrewer/__init__.py
usabrewer/palettes.py
usabrewer-0.0.7.dist-info/WHEEL
usabrewer-0.0.7.dist-info/METADATA
usabrewer-0.0.7.dist-info/RECORD
