Metadata-Version: 2.1
Name: usabrewer
Version: 0.0.7
Summary: Python color palettes based on travel posters from the 50 states
License: MIT
Author: Emma Glass
Requires-Python: >=3.8,<4.0
Classifier: License :: OSI Approved :: MIT License
Classifier: Programming Language :: Python :: 3
Classifier: Programming Language :: Python :: 3.8
Classifier: Programming Language :: Python :: 3.9
Classifier: Programming Language :: Python :: 3.10
Classifier: Programming Language :: Python :: 3.11
